floatplane/__init__.py
floatplane/imageTransfer.py
floatplane-0.0.1.dist-info/LICENSE
floatplane-0.0.1.dist-info/METADATA
floatplane-0.0.1.dist-info/WHEEL
floatplane-0.0.1.dist-info/top_level.txt
floatplane-0.0.1.dist-info/RECORD
